metasim/__init__.py
metasim/constants.py
metasim/types.py
metasim/data/quick_start/.gitignore
metasim/data/quick_start/assets/COMMON/frame/usd/frame.usd
metasim/data/quick_start/assets/rlbench/close_box/box_base/mjcf/box_base_unique.mjcf
metasim/data/quick_start/assets/rlbench/close_box/box_base/urdf/box_base_unique.urdf
metasim/data/quick_start/assets/rlbench/close_box/box_base/usd/box_base.usd
metasim/data/quick_start/materials/Ash.mdl
metasim/data/quick_start/materials/README.md
metasim/data/quick_start/materials/Ash/Ash_BaseColor.png
metasim/data/quick_start/materials/Ash/Ash_H.png
metasim/data/quick_start/materials/Ash/Ash_Normal.png
metasim/data/quick_start/materials/Ash/Ash_ORM.png
metasim/data/quick_start/trajs/rlbench/close_box/v2/franka_v2.pkl.gz
metasim/data/quick_start/trajs/rlbench/close_box/v2/iiwa_v2.pkl.gz
metasim/data/quick_start/trajs/rlbench/close_box/v2/sawyer_v2.pkl.gz
metasim/data/quick_start/trajs/rlbench/close_box/v2/ur5e_2f85_v2.pkl.gz
metasim/queries/base.py
metasim/queries/site.py
metasim/sim/__init__.py
metasim/sim/base.py
metasim/sim/hybrid.py
metasim/sim/parallel.py
metasim/sim/blender/__init__.py
metasim/sim/blender/blender.py
metasim/sim/blender/utils/__init__.py
metasim/sim/blender/utils/camera_util.py
metasim/sim/blender/utils/common_util.py
metasim/sim/genesis/__init__.py
metasim/sim/genesis/genesis.py
metasim/sim/isaacgym/__init__.py
metasim/sim/isaacgym/isaacgym.py
metasim/sim/isaaclab/__init__.py
metasim/sim/isaaclab/empty_env.py
metasim/sim/isaaclab/env_overwriter.py
metasim/sim/isaaclab/isaaclab.py
metasim/sim/isaaclab/isaaclab_helper.py
metasim/sim/isaaclab/cfg/randomization/camera_pos_candidates.txt
metasim/sim/isaaclab/cfg/randomization/ground_mdl_paths.yml
metasim/sim/isaaclab/cfg/randomization/table_mdl_paths.yml
metasim/sim/isaaclab/cfg/randomization/wall_mdl_paths.yml
metasim/sim/isaaclab/utils/camera_random_util.py
metasim/sim/isaaclab/utils/custom_cuboid.py
metasim/sim/isaaclab/utils/custom_direct_rl_env.py
metasim_core-0.1.0.dist-info/METADATA
metasim_core-0.1.0.dist-info/WHEEL
metasim_core-0.1.0.dist-info/top_level.txt
metasim_core-0.1.0.dist-info/RECORD
